[
    [
        {
            "box": [
                98.65591430664062,
                145.52352905273438,
                308.4998474121094,
                352.2482604980469
            ],
            "confidence": 0.9737169146537781,
            "class_id": 0,
            "class_name": "circle"
        },
        {
            "box": [
                202.3837890625,
                197.37667846679688,
                274.1968688964844,
                250.1772918701172
            ],
            "confidence": 0.942356526851654,
            "class_id": 2,
            "class_name": "minutes"
        },
        {
            "box": [
                151.05795288085938,
                211.5085906982422,
                203.2801971435547,
                249.12887573242188
            ],
            "confidence": 0.9220557808876038,
            "class_id": 1,
            "class_name": "hours"
        },
        {
            "box": [
                198.6224822998047,
                150.11160278320312,
                205.9857635498047,
                178.10687255859375
            ],
            "confidence": 0.7743401527404785,
            "class_id": 4,
            "class_name": "12"
        }
    ]
]