[
    [
        {
            "box": [
                53.0305290222168,
                109.07097625732422,
                342.12786865234375,
                397.43206787109375
            ],
            "confidence": 0.9538237452507019,
            "class_id": 0,
            "class_name": "circle"
        },
        {
            "box": [
                195.9376678466797,
                189.1931610107422,
                281.321044921875,
                253.64840698242188
            ],
            "confidence": 0.9351010322570801,
            "class_id": 2,
            "class_name": "minutes"
        },
        {
            "box": [
                139.71588134765625,
                211.6004638671875,
                197.98834228515625,
                253.938720703125
            ],
            "confidence": 0.9039813280105591,
            "class_id": 1,
            "class_name": "hours"
        },
        {
            "box": [
                189.0842742919922,
                120.11491394042969,
                201.62179565429688,
                165.54684448242188
            ],
            "confidence": 0.8292439579963684,
            "class_id": 4,
            "class_name": "12"
        }
    ]
]