[
    [
        {
            "box": [
                135.39068603515625,
                118.36965942382812,
                321.00823974609375,
                301.16497802734375
            ],
            "confidence": 0.9517861604690552,
            "class_id": 0,
            "class_name": "circle"
        },
        {
            "box": [
                231.86477661132812,
                162.3309783935547,
                296.2852478027344,
                211.21287536621094
            ],
            "confidence": 0.9304237961769104,
            "class_id": 2,
            "class_name": "minutes"
        },
        {
            "box": [
                182.43531799316406,
                176.1799774169922,
                224.31463623046875,
                208.2891845703125
            ],
            "confidence": 0.9160283803939819,
            "class_id": 1,
            "class_name": "hours"
        },
        {
            "box": [
                215.45767211914062,
                124.67219543457031,
                240.54017639160156,
                161.82080078125
            ],
            "confidence": 0.8879176378250122,
            "class_id": 4,
            "class_name": "12"
        },
        {
            "box": [
                226.06671142578125,
                142.42042541503906,
                230.27149963378906,
                205.19168090820312
            ],
            "confidence": 0.6165140271186829,
            "class_id": 3,
            "class_name": "seconds"
        }
    ]
]