[
    [
        {
            "box": [
                142.8870849609375,
                572.8734741210938,
                2043.29150390625,
                2380.409912109375
            ],
            "confidence": 0.9322097897529602,
            "class_id": 0,
            "class_name": "circle"
        },
        {
            "box": [
                854.4358520507812,
                1116.650634765625,
                1316.305419921875,
                1893.607177734375
            ],
            "confidence": 0.8561831712722778,
            "class_id": 3,
            "class_name": "seconds"
        }
    ]
]