[
    [
        {
            "box": [
                210.70516967773438,
                435.0451354980469,
                410.2577819824219,
                635.9951171875
            ],
            "confidence": 0.9427651166915894,
            "class_id": 0,
            "class_name": "circle"
        },
        {
            "box": [
                302.0946960449219,
                537.7711181640625,
                321.54888916015625,
                586.092529296875
            ],
            "confidence": 0.5856994390487671,
            "class_id": 1,
            "class_name": "hours"
        },
        {
            "box": [
                241.7113494873047,
                530.031494140625,
                314.9634704589844,
                553.7196044921875
            ],
            "confidence": 0.7956990599632263,
            "class_id": 2,
            "class_name": "minutes"
        },
        {
            "box": [
                261.05029296875,
                473.0870056152344,
                315.44354248046875,
                529.753173828125
            ],
            "confidence": 0.6353329420089722,
            "class_id": 3,
            "class_name": "seconds"
        }
    ]
]